setup.py
PyLucid_boot.egg-info/PKG-INFO
PyLucid_boot.egg-info/SOURCES.txt
PyLucid_boot.egg-info/dependency_links.txt
PyLucid_boot.egg-info/top_level.txt
PyLucid_boot.egg-info/zip-safe
pylucid_boot/__init__.py
pylucid_boot/create_bootstrap_script.py
pylucid_boot/create_standalone_package.py
pylucid_boot/pylucid-boot.py
pylucid_boot/source-pylucid-boot.py