Metadata-Version: 1.0
Name: PyLucid-boot
Version: 0.1.0.20101005.1559
Summary: PyLucid-boot are some scripts for creating a PyLucid virtual environment
Home-page: http://github.com/jedie/PyLucid-boot
Author: Jens Diemer
Author-email: PyLucid-boot@jensdiemer.de
License: UNKNOWN
Platform: any
Classifier: Development Status :: 1 - Planning
Classifier: Development Status :: 2 - Pre-Alpha
Classifier: Environment :: Web Environment
Classifier: Intended Audience :: Developers
Classifier: License :: OSI Approved :: GNU General Public License (GPL)
Classifier: Programming Language :: Python
Classifier: Framework :: Django
Classifier: Topic :: Database :: Front-Ends
Classifier: Topic :: Documentation
Classifier: Topic :: Internet :: WWW/HTTP :: Dynamic Content
Classifier: Topic :: Internet :: WWW/HTTP :: WSGI :: Application
Classifier: Operating System :: OS Independent
